synnamon/__init__.py
synnamon/get_syns.py
synnamon/data/__init__.py
synnamon/data/en_thesaurus.db
synnamon-0.1.8.dist-info/LICENSE.md
synnamon-0.1.8.dist-info/METADATA
synnamon-0.1.8.dist-info/WHEEL
synnamon-0.1.8.dist-info/top_level.txt
synnamon-0.1.8.dist-info/RECORD
