Metadata-Version: 2.1
Name: synnamon
Version: 0.1.8
Summary: Pure Python package for getting synonyms for words.
Home-page: https://github.com/eddiethedean/synnamon
Author: Odos Matthews
Author-email: odosmatthews@gmail.com
License: MIT
Classifier: License :: OSI Approved :: MIT License
Classifier: Programming Language :: Python :: 3
Classifier: Programming Language :: Python :: 3.6
Requires-Python: >=3.6
License-File: LICENSE.md
Requires-Dist: inflex
